opendssdirect/ActiveClass.py
opendssdirect/Bases.py
opendssdirect/Basic.py
opendssdirect/Bus.py
opendssdirect/CNData.py
opendssdirect/CapControls.py
opendssdirect/Capacitors.py
opendssdirect/Circuit.py
opendssdirect/CktElement.py
opendssdirect/CtrlQueue.py
opendssdirect/DSSCore.py
opendssdirect/Element.py
opendssdirect/Error.py
opendssdirect/Executive.py
opendssdirect/Fuses.py
opendssdirect/GICSources.py
opendssdirect/Generators.py
opendssdirect/Isource.py
opendssdirect/LineCodes.py
opendssdirect/LineGeometries.py
opendssdirect/LineSpacings.py
opendssdirect/Lines.py
opendssdirect/LoadShape.py
opendssdirect/Loads.py
opendssdirect/Meters.py
opendssdirect/Monitors.py
opendssdirect/OpenDSSDirect.py
opendssdirect/PDElements.py
opendssdirect/PVsystems.py
opendssdirect/Parallel.py
opendssdirect/Parser.py
opendssdirect/Progress.py
opendssdirect/Properties.py
opendssdirect/Reactors.py
opendssdirect/Reclosers.py
opendssdirect/ReduceCkt.py
opendssdirect/RegControls.py
opendssdirect/Relays.py
opendssdirect/Sensors.py
opendssdirect/Settings.py
opendssdirect/Solution.py
opendssdirect/Storages.py
opendssdirect/SwtControls.py
opendssdirect/TSData.py
opendssdirect/Text.py
opendssdirect/Topology.py
opendssdirect/Transformers.py
opendssdirect/Vsources.py
opendssdirect/WireData.py
opendssdirect/XYCurves.py
opendssdirect/YMatrix.py
opendssdirect/ZIP.py
opendssdirect/__init__.py
opendssdirect/_utils.py
opendssdirect/_version.py
opendssdirect/enums.py
opendssdirect/utils.py
opendssdirect_py-0.9.3.dist-info/METADATA
opendssdirect_py-0.9.3.dist-info/WHEEL
opendssdirect_py-0.9.3.dist-info/licenses/LICENSE
opendssdirect_py-0.9.3.dist-info/RECORD
