Metadata-Version: 2.3
Name: opendssdirect.py
Version: 0.9.3
Summary: Python direct-mode interface to the alternative implementation of OpenDSS from DSS-Extensions.org
Project-URL: Homepage, https://github.com/dss-extensions/OpenDSSDirect.py
Project-URL: Documentation, https://dss-extensions.org/OpenDSSDirect.py
Project-URL: Repository, https://github.com/dss-extensions/OpenDSSDirect.py.git
Project-URL: Bug Tracker, https://github.com/dss-extensions/OpenDSSDirect.py/issues
Author-email: Dheepak Krishnamurthy <me@kdheepak.com>, Paulo Meira <pmeira@ieee.org>
Maintainer-email: Dheepak Krishnamurthy <me@kdheepak.com>, Paulo Meira <pmeira@ieee.org>
License: Copyright 2017 Alliance for Sustainable Energy, LLC
License-File: LICENSE
Keywords: altdss,cffi,electric power systems,opendss,opendssdirect
Classifier: Development Status :: 5 - Production/Stable
Classifier: Intended Audience :: Developers
Classifier: Intended Audience :: Education
Classifier: Intended Audience :: Science/Research
Classifier: License :: Other/Proprietary License
Classifier: Programming Language :: Python :: 3.7
Classifier: Programming Language :: Python :: 3.8
Classifier: Programming Language :: Python :: 3.9
Classifier: Programming Language :: Python :: 3.10
Classifier: Programming Language :: Python :: 3.11
Classifier: Programming Language :: Python :: 3.12
Classifier: Programming Language :: Python :: Implementation :: CPython
Classifier: Programming Language :: Python :: Implementation :: PyPy
Classifier: Topic :: Scientific/Engineering
Classifier: Topic :: Software Development :: Build Tools
Requires-Python: >=3.7
Requires-Dist: dss-python==0.15.6
Provides-Extra: extras
Requires-Dist: altdss; extra == 'extras'
Requires-Dist: matplotlib; extra == 'extras'
Requires-Dist: networkx; extra == 'extras'
Requires-Dist: pandas; extra == 'extras'
Requires-Dist: scipy; extra == 'extras'
